eth_abi/__init__.py
eth_abi/abi.py
eth_abi/base.py
eth_abi/constants.py
eth_abi/decoding.py
eth_abi/encoding.py
eth_abi/exceptions.py
eth_abi/grammar.py
eth_abi/registry.py
eth_abi/utils/__init__.py
eth_abi/utils/numeric.py
eth_abi/utils/padding.py
eth_abi/utils/parsing.py
veriteos_eth_abi-1.2.0.post0.dist-info/METADATA
veriteos_eth_abi-1.2.0.post0.dist-info/RECORD
veriteos_eth_abi-1.2.0.post0.dist-info/WHEEL
veriteos_eth_abi-1.2.0.post0.dist-info/top_level.txt
