Metadata-Version: 2.1
Name: veriteos-eth-abi
Version: 1.2.0.post0
Summary: Veriteos Ethereum ABI Utils
Home-page: https://github.com/veriteos/eth-abi
Author: Kyloon Chuah
Author-email: kyloon@veriteos.com
License: MIT
Keywords: ethereum
Platform: UNKNOWN
Classifier: Development Status :: 5 - Production/Stable
Classifier: Intended Audience :: Developers
Classifier: License :: OSI Approved :: BSD License
Classifier: Natural Language :: English
Classifier: Programming Language :: Python :: 3
Classifier: Programming Language :: Python :: 3.5
Classifier: Programming Language :: Python :: 3.6
Classifier: Programming Language :: Python :: Implementation :: PyPy
Provides-Extra: doc
Requires-Dist: eth-utils (<2.0.0,>=1.2.0)
Requires-Dist: eth-typing (<=2)
Requires-Dist: parsimonious (==0.8.0)
Provides-Extra: doc
Requires-Dist: Sphinx (<2,>=1.6.5); extra == 'doc'
Requires-Dist: sphinx-rtd-theme (>=0.1.9); extra == 'doc'
